{
    "level": "Info",
    "analyzer": "UnsafeDataflow",
    "op_type": "Transmute",
    "description": "Potential unsafe dataflow issue in `mut_bump_vec_rev::MutBumpVecRev::<T, A>::generic_extend_from_within_clone`",
    "file": "bump-scope-0.17.4/src/mut_bump_vec_rev.rs",
    "start_line": 1626,
    "start_col": 5,
    "end_line": 1671,
    "end_col": 6,
    "code_snippet": "pub(crate) fn generic_extend_from_within_clone<E: ErrorBehavior, R>(&mut self, src: R) -> Result<(), E>\n    where\n        T: Clone,\n        R: RangeBounds<usize>,\n    {\n        let range = polyfill::slice::range(src, ..self.len());\n        let count = range.len();\n\n        self.generic_reserve(count)?;\n\n        if T::IS_ZST {\n            unsafe {\n                // We can materialize ZST's from nothing.\n                #[allow(clippy::uninit_assumed_init)]\n                let fake = ManuallyDrop::new(MaybeUninit::<T>::uninit().assume_init());\n\n                for _ in 0..count {\n                    self.push_unchecked((*fake).clone());\n                }\n\n                return Ok(());\n            }\n        }\n\n        // SAFETY:\n        // - `slice::range` guarantees that the given range is valid for indexing self\n        unsafe {\n            let ptr = self.as_mut_ptr();\n\n            let mut src = ptr.add(range.end);\n            let mut dst = ptr;\n\n            let src_end = src.sub(count);\n\n            while src != src_end {\n                src = src.sub(1);\n                dst = dst.sub(1);\n\n                dst.write((*src).clone());\n\n                self.len += 1;\n            }\n        }\n\n        Ok(())\n    }"
}